LICENSE
README.md
setup.cfg
setup.py
lumnisfactors/KEYS.py
lumnisfactors/__init__.py
lumnisfactors/lumnisfactors.py
lumnisfactors.egg-info/PKG-INFO
lumnisfactors.egg-info/SOURCES.txt
lumnisfactors.egg-info/dependency_links.txt
lumnisfactors.egg-info/requires.txt
lumnisfactors.egg-info/top_level.txt