Metadata-Version: 2.1
Name: lumnisfactors
Version: 0.0.5
Summary: Lumnis Alternative Data
Home-page: https://github.com/lumnisfactors/lumnisfactors-python-api/archive/refs/tags/v0.0.5.tar.gz
Author: Abubakarr Jaye
Author-email: ajaye@lumnis.org
Classifier: Programming Language :: Python :: 3
Classifier: License :: OSI Approved :: MIT License
Classifier: Operating System :: OS Independent
Requires-Python: >=3.6
License-File: LICENSE
